binaryornot-stubs/__init__.pyi
binaryornot-stubs/check.pyi
binaryornot-stubs/helpers.pyi
binaryornot_stubs-0.0.4.dist-info/LICENSE.txt
binaryornot_stubs-0.0.4.dist-info/METADATA
binaryornot_stubs-0.0.4.dist-info/WHEEL
binaryornot_stubs-0.0.4.dist-info/RECORD
